{
  "indexes": [
    {
      "collectionGroup": "articles",
      "queryScope": "COLLECTION_GROUP",
      "fields": [
        {
          "fieldPath": "isPublished",
          "order": "ASCENDING"
        },
        {
          "fieldPath": "createdAt",
          "order": "DESCENDING"
        }
      ]
    },
    {
      "collectionGroup": "articles",
      "queryScope": "COLLECTION_GROUP",
      "fields": [
        {
          "fieldPath": "createdAt",
          "order": "DESCENDING"
        }
      ]
    },
    {
      "collectionGroup": "staff_auctions",
      "queryScope": "COLLECTION",
      "fields": [
        {
          "fieldPath": "status",
          "order": "ASCENDING"
        },
        {
          "fieldPath": "endsAt",
          "order": "ASCENDING"
        }
      ]
    },
    {
      "collectionGroup": "staff_auctions",
      "queryScope": "COLLECTION",
      "fields": [
        {
          "fieldPath": "staffCaption",
          "order": "ASCENDING"
        },
        {
          "fieldPath": "status",
          "order": "ASCENDING"
        },
        {
          "fieldPath": "endsAt",
          "order": "ASCENDING"
        }
      ]
    },
    {
      "collectionGroup": "users",
      "queryScope": "COLLECTION",
      "fields": [
        {
          "fieldPath": "seasonYear",
          "order": "ASCENDING"
        },
        {
          "fieldPath": "totalPoints",
          "order": "DESCENDING"
        }
      ]
    },
    {
      "collectionGroup": "users",
      "queryScope": "COLLECTION",
      "fields": [
        {
          "fieldPath": "isActive",
          "order": "ASCENDING"
        },
        {
          "fieldPath": "totalPoints",
          "order": "DESCENDING"
        }
      ]
    },
    {
      "collectionGroup": "lineups",
      "queryScope": "COLLECTION",
      "fields": [
        {
          "fieldPath": "userId",
          "order": "ASCENDING"
        },
        {
          "fieldPath": "week",
          "order": "ASCENDING"
        }
      ]
    },
    {
      "collectionGroup": "leagues",
      "queryScope": "COLLECTION",
      "fields": [
        {
          "fieldPath": "members",
          "arrayConfig": "CONTAINS"
        },
        {
          "fieldPath": "createdAt",
          "order": "DESCENDING"
        }
      ]
    },
    {
      "collectionGroup": "leagues",
      "queryScope": "COLLECTION",
      "fields": [
        {
          "fieldPath": "isPublic",
          "order": "ASCENDING"
        },
        {
          "fieldPath": "createdAt",
          "order": "DESCENDING"
        }
      ]
    },
    {
      "collectionGroup": "leagues",
      "queryScope": "COLLECTION",
      "fields": [
        {
          "fieldPath": "isActive",
          "order": "ASCENDING"
        },
        {
          "fieldPath": "memberCount",
          "order": "DESCENDING"
        }
      ]
    },
    {
      "collectionGroup": "chat",
      "queryScope": "COLLECTION",
      "fields": [
        {
          "fieldPath": "leagueId",
          "order": "ASCENDING"
        },
        {
          "fieldPath": "createdAt",
          "order": "DESCENDING"
        }
      ]
    },
    {
      "collectionGroup": "trades",
      "queryScope": "COLLECTION",
      "fields": [
        {
          "fieldPath": "status",
          "order": "ASCENDING"
        },
        {
          "fieldPath": "createdAt",
          "order": "DESCENDING"
        }
      ]
    },
    {
      "collectionGroup": "notifications",
      "queryScope": "COLLECTION",
      "fields": [
        {
          "fieldPath": "userId",
          "order": "ASCENDING"
        },
        {
          "fieldPath": "read",
          "order": "ASCENDING"
        },
        {
          "fieldPath": "createdAt",
          "order": "DESCENDING"
        }
      ]
    },
    {
      "collectionGroup": "comments",
      "queryScope": "COLLECTION",
      "fields": [
        {
          "fieldPath": "corpsId",
          "order": "ASCENDING"
        },
        {
          "fieldPath": "createdAt",
          "order": "DESCENDING"
        }
      ]
    },
    {
      "collectionGroup": "reports",
      "queryScope": "COLLECTION",
      "fields": [
        {
          "fieldPath": "status",
          "order": "ASCENDING"
        },
        {
          "fieldPath": "createdAt",
          "order": "DESCENDING"
        }
      ]
    },
    {
      "collectionGroup": "historical_scores",
      "queryScope": "COLLECTION",
      "fields": [
        {
          "fieldPath": "showDate",
          "order": "ASCENDING"
        },
        {
          "fieldPath": "corpsName",
          "order": "ASCENDING"
        }
      ]
    },
    {
      "collectionGroup": "historical_scores",
      "queryScope": "COLLECTION",
      "fields": [
        {
          "fieldPath": "seasonYear",
          "order": "ASCENDING"
        },
        {
          "fieldPath": "totalScore",
          "order": "DESCENDING"
        }
      ]
    },
    {
      "collectionGroup": "news_hub",
      "queryScope": "COLLECTION",
      "fields": [
        {
          "fieldPath": "isPublished",
          "order": "ASCENDING"
        },
        {
          "fieldPath": "createdAt",
          "order": "DESCENDING"
        }
      ]
    },
    {
      "collectionGroup": "news_hub",
      "queryScope": "COLLECTION",
      "fields": [
        {
          "fieldPath": "isPublished",
          "order": "ASCENDING"
        },
        {
          "fieldPath": "category",
          "order": "ASCENDING"
        },
        {
          "fieldPath": "createdAt",
          "order": "DESCENDING"
        }
      ]
    },
    {
      "collectionGroup": "profile",
      "queryScope": "COLLECTION",
      "fields": [
        {
          "fieldPath": "engagement.lastLogin",
          "order": "ASCENDING"
        },
        {
          "fieldPath": "engagement.loginStreak",
          "order": "ASCENDING"
        }
      ]
    },
    {
      "collectionGroup": "email_log",
      "queryScope": "COLLECTION",
      "fields": [
        {
          "fieldPath": "emailType",
          "order": "ASCENDING"
        },
        {
          "fieldPath": "sentAt",
          "order": "ASCENDING"
        }
      ]
    },
    {
      "collectionGroup": "news_submissions",
      "queryScope": "COLLECTION",
      "fields": [
        {
          "fieldPath": "status",
          "order": "ASCENDING"
        },
        {
          "fieldPath": "createdAt",
          "order": "DESCENDING"
        }
      ]
    }
  ],
  "fieldOverrides": [
    {
      "collectionGroup": "users",
      "fieldPath": "seasonYear",
      "indexes": [
        {
          "order": "ASCENDING",
          "queryScope": "COLLECTION"
        }
      ]
    },
    {
      "collectionGroup": "leagues",
      "fieldPath": "members",
      "indexes": [
        {
          "arrayConfig": "CONTAINS",
          "queryScope": "COLLECTION"
        }
      ]
    },
    {
      "collectionGroup": "profile",
      "fieldPath": "activeSeasonId",
      "indexes": [
        {
          "order": "ASCENDING",
          "queryScope": "COLLECTION_GROUP"
        }
      ]
    }
  ]
}