{
  "meta": {
    "generatedFrom": "pressboxImporter/output",
    "years": [
      "2000",
      "2001",
      "2002",
      "2003",
      "2004",
      "2005",
      "2006",
      "2007",
      "2008",
      "2009",
      "2010",
      "2011",
      "2012"
    ],
    "corpsSeasons": 802,
    "captions": [
      "GE1",
      "GE2",
      "VP",
      "VA",
      "CG",
      "B",
      "MA",
      "P"
    ],
    "seasonDays": 49,
    "phases": [
      {
        "key": "early",
        "fromDay": 1,
        "toDay": 14
      },
      {
        "key": "mid",
        "fromDay": 15,
        "toDay": 35
      },
      {
        "key": "late",
        "fromDay": 36,
        "toDay": 49
      }
    ],
    "model": "score(d) = L / (1 + exp(-k*(d - d0)))"
  },
  "bands": {
    "GE1": [
      {
        "n": 272,
        "p5": 7.275,
        "p25": 10.633,
        "p50": 12.8,
        "p75": 14.267,
        "p95": 15.825,
        "max": 16.567
      },
      {
        "n": 106,
        "p5": 7.715,
        "p25": 11.133,
        "p50": 13.083,
        "p75": 14.533,
        "p95": 15.922,
        "max": 16.567
      },
      {
        "n": 163,
        "p5": 8.368,
        "p25": 11.833,
        "p50": 13.467,
        "p75": 14.833,
        "p95": 16.035,
        "max": 16.733
      },
      {
        "n": 113,
        "p5": 8.402,
        "p25": 12.033,
        "p50": 13.633,
        "p75": 14.8,
        "p95": 16.177,
        "max": 17.1
      },
      {
        "n": 136,
        "p5": 8.813,
        "p25": 12.3,
        "p50": 13.767,
        "p75": 14.9,
        "p95": 16.328,
        "max": 17.333
      },
      {
        "n": 332,
        "p5": 8.768,
        "p25": 12.133,
        "p50": 13.667,
        "p75": 14.9,
        "p95": 16.415,
        "max": 17.467
      },
      {
        "n": 406,
        "p5": 8.56,
        "p25": 11.967,
        "p50": 13.6,
        "p75": 14.9,
        "p95": 16.382,
        "max": 17.267
      },
      {
        "n": 252,
        "p5": 7.875,
        "p25": 11.642,
        "p50": 13.683,
        "p75": 15.025,
        "p95": 16.467,
        "max": 17.267
      },
      {
        "n": 170,
        "p5": 8.1,
        "p25": 12.108,
        "p50": 13.983,
        "p75": 15.225,
        "p95": 16.7,
        "max": 17.333
      },
      {
        "n": 141,
        "p5": 7.69,
        "p25": 12.175,
        "p50": 14.05,
        "p75": 15.308,
        "p95": 16.777,
        "max": 17.367
      },
      {
        "n": 175,
        "p5": 8.15,
        "p25": 12.367,
        "p50": 14.067,
        "p75": 15.333,
        "p95": 16.877,
        "max": 17.467
      },
      {
        "n": 167,
        "p5": 8.017,
        "p25": 12.267,
        "p50": 14.067,
        "p75": 15.467,
        "p95": 16.957,
        "max": 17.433
      },
      {
        "n": 213,
        "p5": 8.293,
        "p25": 12.033,
        "p50": 14.167,
        "p75": 15.617,
        "p95": 17.113,
        "max": 17.733
      },
      {
        "n": 401,
        "p5": 8.013,
        "p25": 11.867,
        "p50": 14.167,
        "p75": 15.633,
        "p95": 17.113,
        "max": 18.167
      },
      {
        "n": 249,
        "p5": 8.947,
        "p25": 12.167,
        "p50": 14.4,
        "p75": 15.767,
        "p95": 17.133,
        "max": 18.2
      },
      {
        "n": 133,
        "p5": 9.835,
        "p25": 12.767,
        "p50": 14.7,
        "p75": 15.967,
        "p95": 17.3,
        "max": 18.2
      },
      {
        "n": 174,
        "p5": 10.122,
        "p25": 13.333,
        "p50": 14.933,
        "p75": 16.25,
        "p95": 17.433,
        "max": 17.833
      },
      {
        "n": 171,
        "p5": 9.575,
        "p25": 13.533,
        "p50": 15.033,
        "p75": 16.317,
        "p95": 17.443,
        "max": 18
      },
      {
        "n": 95,
        "p5": 9.305,
        "p25": 13.433,
        "p50": 15.033,
        "p75": 16.417,
        "p95": 17.477,
        "max": 18.1
      },
      {
        "n": 212,
        "p5": 9.548,
        "p25": 13.283,
        "p50": 15.033,
        "p75": 16.367,
        "p95": 17.577,
        "max": 18.233
      },
      {
        "n": 427,
        "p5": 9.653,
        "p25": 12.875,
        "p50": 14.917,
        "p75": 16.333,
        "p95": 17.708,
        "max": 18.233
      },
      {
        "n": 216,
        "p5": 10.435,
        "p25": 13.342,
        "p50": 15.117,
        "p75": 16.5,
        "p95": 17.808,
        "max": 18.267
      },
      {
        "n": 201,
        "p5": 11.322,
        "p25": 13.858,
        "p50": 15.383,
        "p75": 16.725,
        "p95": 17.908,
        "max": 18.4
      },
      {
        "n": 210,
        "p5": 12.137,
        "p25": 14.35,
        "p50": 15.7,
        "p75": 16.892,
        "p95": 18,
        "max": 18.567
      },
      {
        "n": 163,
        "p5": 12.303,
        "p25": 14.437,
        "p50": 15.817,
        "p75": 16.917,
        "p95": 18.033,
        "max": 18.767
      },
      {
        "n": 226,
        "p5": 11.607,
        "p25": 14.404,
        "p50": 15.95,
        "p75": 17.025,
        "p95": 18.067,
        "max": 18.783
      },
      {
        "n": 158,
        "p5": 10.652,
        "p25": 14.087,
        "p50": 15.817,
        "p75": 17.058,
        "p95": 18.158,
        "max": 18.95
      },
      {
        "n": 392,
        "p5": 10.007,
        "p25": 13.8,
        "p50": 15.633,
        "p75": 17,
        "p95": 18.239,
        "max": 18.983
      },
      {
        "n": 172,
        "p5": 11.052,
        "p25": 14,
        "p50": 15.733,
        "p75": 17.033,
        "p95": 18.361,
        "max": 19.067
      },
      {
        "n": 168,
        "p5": 11.955,
        "p25": 14.4,
        "p50": 15.9,
        "p75": 17.175,
        "p95": 18.437,
        "max": 19
      },
      {
        "n": 212,
        "p5": 12.05,
        "p25": 14.583,
        "p50": 16.067,
        "p75": 17.308,
        "p95": 18.488,
        "max": 19.033
      },
      {
        "n": 167,
        "p5": 12.097,
        "p25": 14.583,
        "p50": 15.95,
        "p75": 17.242,
        "p95": 18.4,
        "max": 19.133
      },
      {
        "n": 166,
        "p5": 12.208,
        "p25": 14.717,
        "p50": 16.183,
        "p75": 17.433,
        "p95": 18.533,
        "max": 19.267
      },
      {
        "n": 221,
        "p5": 12.155,
        "p25": 14.692,
        "p50": 16.217,
        "p75": 17.375,
        "p95": 18.6,
        "max": 19.3
      },
      {
        "n": 479,
        "p5": 11.81,
        "p25": 14.825,
        "p50": 16.467,
        "p75": 17.542,
        "p95": 18.8,
        "max": 19.367
      },
      {
        "n": 229,
        "p5": 11.163,
        "p25": 14.525,
        "p50": 16.167,
        "p75": 17.308,
        "p95": 18.667,
        "max": 19.333
      },
      {
        "n": 353,
        "p5": 11.267,
        "p25": 14.7,
        "p50": 16.2,
        "p75": 17.4,
        "p95": 18.675,
        "max": 19.367
      },
      {
        "n": 256,
        "p5": 11.232,
        "p25": 14.533,
        "p50": 16.067,
        "p75": 17.333,
        "p95": 18.675,
        "max": 19.333
      },
      {
        "n": 288,
        "p5": 11.978,
        "p25": 14.867,
        "p50": 16.383,
        "p75": 17.567,
        "p95": 18.842,
        "max": 19.467
      },
      {
        "n": 318,
        "p5": 11.872,
        "p25": 14.8,
        "p50": 16.417,
        "p75": 17.6,
        "p95": 18.92,
        "max": 19.6
      },
      {
        "n": 373,
        "p5": 12.393,
        "p25": 15.2,
        "p50": 16.65,
        "p75": 17.833,
        "p95": 19.053,
        "max": 19.8
      },
      {
        "n": 300,
        "p5": 12.232,
        "p25": 15.2,
        "p50": 16.633,
        "p75": 17.8,
        "p95": 19.053,
        "max": 19.7
      },
      {
        "n": 304,
        "p5": 12.348,
        "p25": 15.283,
        "p50": 16.733,
        "p75": 17.933,
        "p95": 19.1,
        "max": 19.7
      },
      {
        "n": 144,
        "p5": 11.382,
        "p25": 14.95,
        "p50": 16.533,
        "p75": 17.8,
        "p95": 19,
        "max": 19.567
      },
      {
        "n": 281,
        "p5": 12.53,
        "p25": 15.617,
        "p50": 17.033,
        "p75": 18.1,
        "p95": 19.2,
        "max": 19.7
      },
      {
        "n": 37,
        "p5": 13.178,
        "p25": 15.8,
        "p50": 17.2,
        "p75": 18.208,
        "p95": 19.308,
        "max": 19.667
      },
      {
        "n": 351,
        "p5": 14.728,
        "p25": 16.367,
        "p50": 17.567,
        "p75": 18.525,
        "p95": 19.525,
        "max": 19.8
      },
      {
        "n": 281,
        "p5": 14.908,
        "p25": 16.404,
        "p50": 17.567,
        "p75": 18.625,
        "p95": 19.542,
        "max": 19.867
      },
      {
        "n": 230,
        "p5": 16.05,
        "p25": 17.042,
        "p50": 17.967,
        "p75": 18.883,
        "p95": 19.617,
        "max": 19.967
      }
    ],
    "GE2": [
      {
        "n": 272,
        "p5": 7.352,
        "p25": 11.133,
        "p50": 13.033,
        "p75": 14.358,
        "p95": 15.825,
        "max": 16.633
      },
      {
        "n": 106,
        "p5": 7.997,
        "p25": 11.5,
        "p50": 13.333,
        "p75": 14.642,
        "p95": 15.955,
        "max": 16.767
      },
      {
        "n": 163,
        "p5": 8.395,
        "p25": 11.733,
        "p50": 13.667,
        "p75": 14.942,
        "p95": 16.035,
        "max": 16.867
      },
      {
        "n": 113,
        "p5": 8.337,
        "p25": 11.658,
        "p50": 13.833,
        "p75": 15.083,
        "p95": 16.143,
        "max": 16.9
      },
      {
        "n": 136,
        "p5": 8.503,
        "p25": 11.858,
        "p50": 13.8,
        "p75": 15.075,
        "p95": 16.147,
        "max": 16.967
      },
      {
        "n": 332,
        "p5": 8.65,
        "p25": 12.058,
        "p50": 13.767,
        "p75": 15.075,
        "p95": 16.233,
        "max": 17.067
      },
      {
        "n": 406,
        "p5": 8.518,
        "p25": 12.058,
        "p50": 13.667,
        "p75": 14.975,
        "p95": 16.315,
        "max": 17.233
      },
      {
        "n": 252,
        "p5": 7.978,
        "p25": 11.892,
        "p50": 13.733,
        "p75": 15.033,
        "p95": 16.4,
        "max": 17.2
      },
      {
        "n": 170,
        "p5": 8.078,
        "p25": 12.292,
        "p50": 13.933,
        "p75": 15.2,
        "p95": 16.567,
        "max": 17.3
      },
      {
        "n": 141,
        "p5": 7.74,
        "p25": 12.183,
        "p50": 13.9,
        "p75": 15.233,
        "p95": 16.628,
        "max": 17.367
      },
      {
        "n": 175,
        "p5": 8.08,
        "p25": 12.417,
        "p50": 13.967,
        "p75": 15.35,
        "p95": 16.735,
        "max": 17.467
      },
      {
        "n": 166,
        "p5": 8.04,
        "p25": 12.483,
        "p50": 14.033,
        "p75": 15.35,
        "p95": 16.815,
        "max": 17.433
      },
      {
        "n": 213,
        "p5": 8.26,
        "p25": 12.467,
        "p50": 14.233,
        "p75": 15.517,
        "p95": 16.905,
        "max": 17.433
      },
      {
        "n": 401,
        "p5": 8.153,
        "p25": 12.333,
        "p50": 14.3,
        "p75": 15.533,
        "p95": 16.913,
        "max": 17.433
      },
      {
        "n": 249,
        "p5": 9.087,
        "p25": 12.467,
        "p50": 14.467,
        "p75": 15.733,
        "p95": 16.933,
        "max": 17.5
      },
      {
        "n": 133,
        "p5": 9.563,
        "p25": 12.967,
        "p50": 14.733,
        "p75": 15.9,
        "p95": 17.045,
        "max": 17.667
      },
      {
        "n": 174,
        "p5": 9.837,
        "p25": 13.3,
        "p50": 14.967,
        "p75": 16.1,
        "p95": 17.178,
        "max": 17.767
      },
      {
        "n": 171,
        "p5": 9.41,
        "p25": 13.317,
        "p50": 15,
        "p75": 16.217,
        "p95": 17.245,
        "max": 17.8
      },
      {
        "n": 95,
        "p5": 9.288,
        "p25": 13.217,
        "p50": 14.967,
        "p75": 16.225,
        "p95": 17.233,
        "max": 17.867
      },
      {
        "n": 212,
        "p5": 9.255,
        "p25": 13.017,
        "p50": 14.867,
        "p75": 16.192,
        "p95": 17.3,
        "max": 18.1
      },
      {
        "n": 427,
        "p5": 9.28,
        "p25": 12.8,
        "p50": 14.767,
        "p75": 16.042,
        "p95": 17.375,
        "max": 18.333
      },
      {
        "n": 216,
        "p5": 10.258,
        "p25": 13.167,
        "p50": 14.967,
        "p75": 16.2,
        "p95": 17.542,
        "max": 18.4
      },
      {
        "n": 201,
        "p5": 11.158,
        "p25": 13.808,
        "p50": 15.317,
        "p75": 16.5,
        "p95": 17.675,
        "max": 18.467
      },
      {
        "n": 210,
        "p5": 11.667,
        "p25": 14.325,
        "p50": 15.617,
        "p75": 16.733,
        "p95": 17.733,
        "max": 18.467
      },
      {
        "n": 163,
        "p5": 11.8,
        "p25": 14.492,
        "p50": 15.75,
        "p75": 16.867,
        "p95": 17.8,
        "max": 18.633
      },
      {
        "n": 226,
        "p5": 11.228,
        "p25": 14.292,
        "p50": 15.867,
        "p75": 16.925,
        "p95": 17.869,
        "max": 18.6
      },
      {
        "n": 158,
        "p5": 10.662,
        "p25": 13.904,
        "p50": 15.7,
        "p75": 16.946,
        "p95": 17.977,
        "max": 18.667
      },
      {
        "n": 392,
        "p5": 10.068,
        "p25": 13.471,
        "p50": 15.533,
        "p75": 16.912,
        "p95": 18.077,
        "max": 18.6
      },
      {
        "n": 172,
        "p5": 10.687,
        "p25": 13.821,
        "p50": 15.55,
        "p75": 16.954,
        "p95": 18.174,
        "max": 18.7
      },
      {
        "n": 168,
        "p5": 11.438,
        "p25": 14.192,
        "p50": 15.817,
        "p75": 17.133,
        "p95": 18.3,
        "max": 18.733
      },
      {
        "n": 212,
        "p5": 11.838,
        "p25": 14.492,
        "p50": 16.017,
        "p75": 17.217,
        "p95": 18.323,
        "max": 18.767
      },
      {
        "n": 167,
        "p5": 12.108,
        "p25": 14.442,
        "p50": 16.033,
        "p75": 17.117,
        "p95": 18.257,
        "max": 18.833
      },
      {
        "n": 166,
        "p5": 12.057,
        "p25": 14.475,
        "p50": 16.267,
        "p75": 17.25,
        "p95": 18.357,
        "max": 19.05
      },
      {
        "n": 221,
        "p5": 11.677,
        "p25": 14.467,
        "p50": 16.233,
        "p75": 17.242,
        "p95": 18.433,
        "max": 19.2
      },
      {
        "n": 479,
        "p5": 11.287,
        "p25": 14.558,
        "p50": 16.367,
        "p75": 17.408,
        "p95": 18.6,
        "max": 19.3
      },
      {
        "n": 229,
        "p5": 10.787,
        "p25": 14.358,
        "p50": 16.067,
        "p75": 17.275,
        "p95": 18.6,
        "max": 19.317
      },
      {
        "n": 353,
        "p5": 11.185,
        "p25": 14.5,
        "p50": 16.2,
        "p75": 17.433,
        "p95": 18.733,
        "max": 19.4
      },
      {
        "n": 256,
        "p5": 10.903,
        "p25": 14.233,
        "p50": 16.133,
        "p75": 17.433,
        "p95": 18.8,
        "max": 19.433
      },
      {
        "n": 288,
        "p5": 11.398,
        "p25": 14.6,
        "p50": 16.433,
        "p75": 17.6,
        "p95": 18.867,
        "max": 19.5
      },
      {
        "n": 318,
        "p5": 11.213,
        "p25": 14.6,
        "p50": 16.4,
        "p75": 17.6,
        "p95": 18.867,
        "max": 19.6
      },
      {
        "n": 373,
        "p5": 12.128,
        "p25": 15.167,
        "p50": 16.7,
        "p75": 17.9,
        "p95": 19,
        "max": 19.767
      },
      {
        "n": 300,
        "p5": 12.167,
        "p25": 15.233,
        "p50": 16.733,
        "p75": 17.933,
        "p95": 19.095,
        "max": 19.767
      },
      {
        "n": 304,
        "p5": 12.067,
        "p25": 15.367,
        "p50": 16.833,
        "p75": 18,
        "p95": 19.188,
        "max": 19.733
      },
      {
        "n": 145,
        "p5": 11.34,
        "p25": 14.967,
        "p50": 16.617,
        "p75": 17.833,
        "p95": 19.188,
        "max": 19.733
      },
      {
        "n": 281,
        "p5": 12.507,
        "p25": 15.467,
        "p50": 16.983,
        "p75": 18.067,
        "p95": 19.307,
        "max": 19.833
      },
      {
        "n": 37,
        "p5": 13.097,
        "p25": 15.671,
        "p50": 17.15,
        "p75": 18.2,
        "p95": 19.38,
        "max": 19.9
      },
      {
        "n": 350,
        "p5": 14.463,
        "p25": 16.371,
        "p50": 17.567,
        "p75": 18.5,
        "p95": 19.513,
        "max": 19.883
      },
      {
        "n": 281,
        "p5": 14.797,
        "p25": 16.604,
        "p50": 17.692,
        "p75": 18.667,
        "p95": 19.567,
        "max": 19.9
      },
      {
        "n": 230,
        "p5": 16.033,
        "p25": 17.233,
        "p50": 18.117,
        "p75": 18.967,
        "p95": 19.667,
        "max": 19.917
      }
    ],
    "VP": [
      {
        "n": 218,
        "p5": 7.637,
        "p25": 10.242,
        "p50": 12.633,
        "p75": 14.1,
        "p95": 15.822,
        "max": 16.6
      },
      {
        "n": 74,
        "p5": 8.057,
        "p25": 10.775,
        "p50": 12.883,
        "p75": 14.467,
        "p95": 15.892,
        "max": 16.667
      },
      {
        "n": 116,
        "p5": 8.443,
        "p25": 11.208,
        "p50": 13.167,
        "p75": 14.733,
        "p95": 15.853,
        "max": 16.6
      },
      {
        "n": 81,
        "p5": 8,
        "p25": 11.267,
        "p50": 13.333,
        "p75": 14.667,
        "p95": 15.922,
        "max": 16.7
      },
      {
        "n": 93,
        "p5": 8.133,
        "p25": 11.333,
        "p50": 13.367,
        "p75": 14.667,
        "p95": 15.98,
        "max": 16.8
      },
      {
        "n": 245,
        "p5": 8.133,
        "p25": 11.433,
        "p50": 13.383,
        "p75": 14.733,
        "p95": 16.188,
        "max": 16.967
      },
      {
        "n": 316,
        "p5": 7.82,
        "p25": 11.3,
        "p50": 13.283,
        "p75": 14.775,
        "p95": 16.203,
        "max": 16.9
      },
      {
        "n": 184,
        "p5": 7.363,
        "p25": 11.2,
        "p50": 13.483,
        "p75": 14.842,
        "p95": 16.337,
        "max": 17.033
      },
      {
        "n": 147,
        "p5": 7.763,
        "p25": 11.517,
        "p50": 13.85,
        "p75": 15.108,
        "p95": 16.563,
        "max": 17.133
      },
      {
        "n": 100,
        "p5": 7.903,
        "p25": 11.317,
        "p50": 13.883,
        "p75": 15.2,
        "p95": 16.702,
        "max": 17.467
      },
      {
        "n": 137,
        "p5": 8.193,
        "p25": 11.75,
        "p50": 13.817,
        "p75": 15.308,
        "p95": 16.768,
        "max": 17.367
      },
      {
        "n": 116,
        "p5": 7.89,
        "p25": 11.867,
        "p50": 13.833,
        "p75": 15.367,
        "p95": 16.833,
        "max": 17.567
      },
      {
        "n": 190,
        "p5": 7.915,
        "p25": 12,
        "p50": 13.967,
        "p75": 15.5,
        "p95": 16.915,
        "max": 17.633
      },
      {
        "n": 392,
        "p5": 7.947,
        "p25": 11.65,
        "p50": 14.117,
        "p75": 15.558,
        "p95": 16.95,
        "max": 17.767
      },
      {
        "n": 240,
        "p5": 8.857,
        "p25": 11.983,
        "p50": 14.317,
        "p75": 15.7,
        "p95": 16.963,
        "max": 17.767
      },
      {
        "n": 133,
        "p5": 9.505,
        "p25": 12.417,
        "p50": 14.583,
        "p75": 15.858,
        "p95": 17.048,
        "max": 17.7
      },
      {
        "n": 174,
        "p5": 9.94,
        "p25": 13.033,
        "p50": 14.833,
        "p75": 16.125,
        "p95": 17.163,
        "max": 17.933
      },
      {
        "n": 171,
        "p5": 9.403,
        "p25": 13.05,
        "p50": 14.867,
        "p75": 16.175,
        "p95": 17.293,
        "max": 18.067
      },
      {
        "n": 95,
        "p5": 9.383,
        "p25": 13.3,
        "p50": 14.967,
        "p75": 16.15,
        "p95": 17.36,
        "max": 18.233
      },
      {
        "n": 195,
        "p5": 9.297,
        "p25": 13.117,
        "p50": 14.9,
        "p75": 16.067,
        "p95": 17.41,
        "max": 18.3
      },
      {
        "n": 415,
        "p5": 9.545,
        "p25": 12.992,
        "p50": 14.767,
        "p75": 16.058,
        "p95": 17.4,
        "max": 18.3
      },
      {
        "n": 212,
        "p5": 10.298,
        "p25": 13.242,
        "p50": 14.9,
        "p75": 16.358,
        "p95": 17.5,
        "max": 18.4
      },
      {
        "n": 201,
        "p5": 11.152,
        "p25": 13.825,
        "p50": 15.167,
        "p75": 16.542,
        "p95": 17.7,
        "max": 18.367
      },
      {
        "n": 210,
        "p5": 11.9,
        "p25": 14.267,
        "p50": 15.433,
        "p75": 16.717,
        "p95": 17.83,
        "max": 18.567
      },
      {
        "n": 163,
        "p5": 12.042,
        "p25": 14.375,
        "p50": 15.633,
        "p75": 16.842,
        "p95": 17.963,
        "max": 18.667
      },
      {
        "n": 226,
        "p5": 11.608,
        "p25": 14.317,
        "p50": 15.75,
        "p75": 16.975,
        "p95": 18.03,
        "max": 18.8
      },
      {
        "n": 158,
        "p5": 10.908,
        "p25": 14.017,
        "p50": 15.7,
        "p75": 16.925,
        "p95": 18.048,
        "max": 18.833
      },
      {
        "n": 392,
        "p5": 10.337,
        "p25": 13.742,
        "p50": 15.467,
        "p75": 16.808,
        "p95": 18.082,
        "max": 18.867
      },
      {
        "n": 172,
        "p5": 11.193,
        "p25": 13.892,
        "p50": 15.517,
        "p75": 16.842,
        "p95": 18.115,
        "max": 18.8
      },
      {
        "n": 168,
        "p5": 11.815,
        "p25": 14.258,
        "p50": 15.733,
        "p75": 17.075,
        "p95": 18.267,
        "max": 18.8
      },
      {
        "n": 212,
        "p5": 12.075,
        "p25": 14.458,
        "p50": 15.9,
        "p75": 17.133,
        "p95": 18.267,
        "max": 18.733
      },
      {
        "n": 167,
        "p5": 11.952,
        "p25": 14.4,
        "p50": 15.833,
        "p75": 17.092,
        "p95": 18.292,
        "max": 18.967
      },
      {
        "n": 166,
        "p5": 11.563,
        "p25": 14.5,
        "p50": 16.033,
        "p75": 17.225,
        "p95": 18.425,
        "max": 19.1
      },
      {
        "n": 221,
        "p5": 11.397,
        "p25": 14.567,
        "p50": 16.1,
        "p75": 17.258,
        "p95": 18.558,
        "max": 19.3
      },
      {
        "n": 479,
        "p5": 11.31,
        "p25": 14.767,
        "p50": 16.367,
        "p75": 17.467,
        "p95": 18.733,
        "max": 19.333
      },
      {
        "n": 229,
        "p5": 11.13,
        "p25": 14.533,
        "p50": 16.1,
        "p75": 17.267,
        "p95": 18.6,
        "max": 19.267
      },
      {
        "n": 353,
        "p5": 11.267,
        "p25": 14.7,
        "p50": 16.167,
        "p75": 17.342,
        "p95": 18.633,
        "max": 19.233
      },
      {
        "n": 256,
        "p5": 10.743,
        "p25": 14.558,
        "p50": 16.067,
        "p75": 17.242,
        "p95": 18.622,
        "max": 19.267
      },
      {
        "n": 288,
        "p5": 11.157,
        "p25": 14.9,
        "p50": 16.367,
        "p75": 17.5,
        "p95": 18.822,
        "max": 19.5
      },
      {
        "n": 318,
        "p5": 11.177,
        "p25": 14.733,
        "p50": 16.367,
        "p75": 17.592,
        "p95": 18.922,
        "max": 19.733
      },
      {
        "n": 373,
        "p5": 11.953,
        "p25": 15.042,
        "p50": 16.6,
        "p75": 17.825,
        "p95": 19,
        "max": 19.867
      },
      {
        "n": 300,
        "p5": 11.925,
        "p25": 14.933,
        "p50": 16.567,
        "p75": 17.833,
        "p95": 19.033,
        "max": 19.867
      },
      {
        "n": 304,
        "p5": 11.565,
        "p25": 14.633,
        "p50": 16.567,
        "p75": 17.833,
        "p95": 19.027,
        "max": 19.733
      },
      {
        "n": 145,
        "p5": 10.865,
        "p25": 14.233,
        "p50": 16.367,
        "p75": 17.7,
        "p95": 18.96,
        "max": 19.6
      },
      {
        "n": 281,
        "p5": 12.213,
        "p25": 15,
        "p50": 16.8,
        "p75": 18,
        "p95": 19.007,
        "max": 19.533
      },
      {
        "n": 37,
        "p5": 13.053,
        "p25": 15.633,
        "p50": 17.067,
        "p75": 18.217,
        "p95": 19.147,
        "max": 19.667
      },
      {
        "n": 351,
        "p5": 14.287,
        "p25": 16.333,
        "p50": 17.467,
        "p75": 18.583,
        "p95": 19.413,
        "max": 19.833
      },
      {
        "n": 281,
        "p5": 14.633,
        "p25": 16.375,
        "p50": 17.567,
        "p75": 18.683,
        "p95": 19.567,
        "max": 19.933
      },
      {
        "n": 230,
        "p5": 15.833,
        "p25": 17.017,
        "p50": 17.967,
        "p75": 18.967,
        "p95": 19.667,
        "max": 19.933
      }
    ],
    "VA": [
      {
        "n": 272,
        "p5": 7.203,
        "p25": 10.758,
        "p50": 12.8,
        "p75": 14.267,
        "p95": 15.942,
        "max": 16.7
      },
      {
        "n": 106,
        "p5": 8.018,
        "p25": 11.367,
        "p50": 13.167,
        "p75": 14.567,
        "p95": 15.942,
        "max": 16.867
      },
      {
        "n": 163,
        "p5": 8.707,
        "p25": 11.842,
        "p50": 13.5,
        "p75": 14.833,
        "p95": 16.002,
        "max": 16.833
      },
      {
        "n": 113,
        "p5": 8.49,
        "p25": 11.9,
        "p50": 13.517,
        "p75": 14.883,
        "p95": 16.135,
        "max": 16.867
      },
      {
        "n": 136,
        "p5": 8.608,
        "p25": 11.958,
        "p50": 13.517,
        "p75": 14.858,
        "p95": 16.268,
        "max": 16.867
      },
      {
        "n": 332,
        "p5": 8.543,
        "p25": 11.925,
        "p50": 13.517,
        "p75": 14.85,
        "p95": 16.342,
        "max": 17.067
      },
      {
        "n": 406,
        "p5": 8.197,
        "p25": 11.858,
        "p50": 13.533,
        "p75": 14.8,
        "p95": 16.348,
        "max": 17.2
      },
      {
        "n": 252,
        "p5": 7.842,
        "p25": 11.55,
        "p50": 13.567,
        "p75": 14.817,
        "p95": 16.382,
        "max": 17.233
      },
      {
        "n": 170,
        "p5": 8.307,
        "p25": 11.992,
        "p50": 13.75,
        "p75": 15.042,
        "p95": 16.58,
        "max": 17.3
      },
      {
        "n": 142,
        "p5": 8.037,
        "p25": 11.892,
        "p50": 13.85,
        "p75": 15.158,
        "p95": 16.632,
        "max": 17.433
      },
      {
        "n": 175,
        "p5": 8.137,
        "p25": 12.108,
        "p50": 13.817,
        "p75": 15.217,
        "p95": 16.755,
        "max": 17.567
      },
      {
        "n": 167,
        "p5": 8.123,
        "p25": 12.133,
        "p50": 13.9,
        "p75": 15.333,
        "p95": 16.857,
        "max": 17.7
      },
      {
        "n": 213,
        "p5": 8.457,
        "p25": 12.1,
        "p50": 14.033,
        "p75": 15.55,
        "p95": 17.023,
        "max": 17.8
      },
      {
        "n": 401,
        "p5": 8.487,
        "p25": 12.1,
        "p50": 14.167,
        "p75": 15.733,
        "p95": 17.1,
        "max": 18.033
      },
      {
        "n": 249,
        "p5": 9.06,
        "p25": 12.4,
        "p50": 14.367,
        "p75": 15.833,
        "p95": 17.133,
        "max": 18.1
      },
      {
        "n": 133,
        "p5": 9.515,
        "p25": 12.9,
        "p50": 14.567,
        "p75": 15.983,
        "p95": 17.245,
        "max": 18.167
      },
      {
        "n": 174,
        "p5": 9.755,
        "p25": 13.267,
        "p50": 14.9,
        "p75": 16.233,
        "p95": 17.345,
        "max": 18.1
      },
      {
        "n": 171,
        "p5": 9.445,
        "p25": 13.3,
        "p50": 15.033,
        "p75": 16.317,
        "p95": 17.422,
        "max": 18.233
      },
      {
        "n": 95,
        "p5": 9.808,
        "p25": 13.325,
        "p50": 15.067,
        "p75": 16.333,
        "p95": 17.443,
        "max": 18.233
      },
      {
        "n": 212,
        "p5": 9.842,
        "p25": 13.108,
        "p50": 14.933,
        "p75": 16.25,
        "p95": 17.533,
        "max": 18.333
      },
      {
        "n": 427,
        "p5": 9.835,
        "p25": 12.808,
        "p50": 14.767,
        "p75": 16.233,
        "p95": 17.523,
        "max": 18.4
      },
      {
        "n": 216,
        "p5": 10.35,
        "p25": 13.15,
        "p50": 14.967,
        "p75": 16.367,
        "p95": 17.623,
        "max": 18.5
      },
      {
        "n": 201,
        "p5": 11.15,
        "p25": 13.733,
        "p50": 15.267,
        "p75": 16.6,
        "p95": 17.752,
        "max": 18.6
      },
      {
        "n": 210,
        "p5": 11.907,
        "p25": 14.217,
        "p50": 15.567,
        "p75": 16.767,
        "p95": 17.915,
        "max": 18.667
      },
      {
        "n": 163,
        "p5": 11.932,
        "p25": 14.317,
        "p50": 15.733,
        "p75": 16.9,
        "p95": 18.04,
        "max": 18.7
      },
      {
        "n": 226,
        "p5": 11.56,
        "p25": 14.317,
        "p50": 15.883,
        "p75": 17.033,
        "p95": 18.16,
        "max": 18.7
      },
      {
        "n": 158,
        "p5": 10.92,
        "p25": 14.067,
        "p50": 15.817,
        "p75": 17.067,
        "p95": 18.212,
        "max": 18.7
      },
      {
        "n": 392,
        "p5": 10.468,
        "p25": 13.825,
        "p50": 15.55,
        "p75": 17.033,
        "p95": 18.235,
        "max": 18.767
      },
      {
        "n": 172,
        "p5": 11.308,
        "p25": 14.017,
        "p50": 15.567,
        "p75": 17.067,
        "p95": 18.297,
        "max": 18.9
      },
      {
        "n": 168,
        "p5": 11.908,
        "p25": 14.342,
        "p50": 15.733,
        "p75": 17.233,
        "p95": 18.43,
        "max": 19.1
      },
      {
        "n": 212,
        "p5": 12.362,
        "p25": 14.75,
        "p50": 16,
        "p75": 17.333,
        "p95": 18.482,
        "max": 19.133
      },
      {
        "n": 167,
        "p5": 12.218,
        "p25": 14.858,
        "p50": 16,
        "p75": 17.233,
        "p95": 18.415,
        "max": 19.133
      },
      {
        "n": 166,
        "p5": 12.052,
        "p25": 15,
        "p50": 16.267,
        "p75": 17.4,
        "p95": 18.567,
        "max": 19.167
      },
      {
        "n": 221,
        "p5": 11.818,
        "p25": 14.833,
        "p50": 16.3,
        "p75": 17.367,
        "p95": 18.633,
        "max": 19.3
      },
      {
        "n": 479,
        "p5": 11.86,
        "p25": 14.967,
        "p50": 16.533,
        "p75": 17.6,
        "p95": 18.787,
        "max": 19.367
      },
      {
        "n": 229,
        "p5": 11.413,
        "p25": 14.6,
        "p50": 16.2,
        "p75": 17.367,
        "p95": 18.667,
        "max": 19.333
      },
      {
        "n": 353,
        "p5": 11.487,
        "p25": 14.633,
        "p50": 16.233,
        "p75": 17.433,
        "p95": 18.708,
        "max": 19.367
      },
      {
        "n": 256,
        "p5": 10.82,
        "p25": 14.3,
        "p50": 16.1,
        "p75": 17.333,
        "p95": 18.655,
        "max": 19.367
      },
      {
        "n": 287,
        "p5": 11.457,
        "p25": 14.733,
        "p50": 16.333,
        "p75": 17.5,
        "p95": 18.708,
        "max": 19.5
      },
      {
        "n": 318,
        "p5": 11.143,
        "p25": 14.8,
        "p50": 16.4,
        "p75": 17.567,
        "p95": 18.8,
        "max": 19.533
      },
      {
        "n": 373,
        "p5": 11.905,
        "p25": 15.267,
        "p50": 16.667,
        "p75": 17.8,
        "p95": 18.968,
        "max": 19.7
      },
      {
        "n": 300,
        "p5": 11.925,
        "p25": 15.167,
        "p50": 16.667,
        "p75": 17.8,
        "p95": 19.063,
        "max": 19.667
      },
      {
        "n": 304,
        "p5": 11.985,
        "p25": 15.067,
        "p50": 16.667,
        "p75": 17.867,
        "p95": 19.03,
        "max": 19.667
      },
      {
        "n": 145,
        "p5": 11.39,
        "p25": 14.633,
        "p50": 16.433,
        "p75": 17.733,
        "p95": 19.028,
        "max": 19.667
      },
      {
        "n": 281,
        "p5": 12.507,
        "p25": 15.367,
        "p50": 16.933,
        "p75": 18.033,
        "p95": 19.1,
        "max": 19.767
      },
      {
        "n": 37,
        "p5": 13.143,
        "p25": 15.717,
        "p50": 17.067,
        "p75": 18.15,
        "p95": 19.3,
        "max": 19.9
      },
      {
        "n": 351,
        "p5": 14.41,
        "p25": 16.383,
        "p50": 17.433,
        "p75": 18.45,
        "p95": 19.467,
        "max": 19.967
      },
      {
        "n": 281,
        "p5": 14.665,
        "p25": 16.45,
        "p50": 17.5,
        "p75": 18.617,
        "p95": 19.633,
        "max": 20
      },
      {
        "n": 230,
        "p5": 15.897,
        "p25": 17.1,
        "p50": 17.967,
        "p75": 18.933,
        "p95": 19.733,
        "max": 20
      }
    ],
    "CG": [
      {
        "n": 212,
        "p5": 5.637,
        "p25": 9.7,
        "p50": 12.333,
        "p75": 14.233,
        "p95": 15.997,
        "max": 16.533
      },
      {
        "n": 69,
        "p5": 6.108,
        "p25": 10.35,
        "p50": 12.667,
        "p75": 14.567,
        "p95": 16.025,
        "max": 16.633
      },
      {
        "n": 98,
        "p5": 5.982,
        "p25": 10.65,
        "p50": 13.15,
        "p75": 14.867,
        "p95": 16.077,
        "max": 16.633
      },
      {
        "n": 76,
        "p5": 6.535,
        "p25": 11.117,
        "p50": 13.317,
        "p75": 14.933,
        "p95": 16.237,
        "max": 16.833
      },
      {
        "n": 93,
        "p5": 7.218,
        "p25": 11.367,
        "p50": 13.517,
        "p75": 14.933,
        "p95": 16.387,
        "max": 16.933
      },
      {
        "n": 245,
        "p5": 8.108,
        "p25": 11.7,
        "p50": 13.467,
        "p75": 14.867,
        "p95": 16.453,
        "max": 17.1
      },
      {
        "n": 330,
        "p5": 7.858,
        "p25": 11.3,
        "p50": 13.333,
        "p75": 14.833,
        "p95": 16.427,
        "max": 17.067
      },
      {
        "n": 183,
        "p5": 7.225,
        "p25": 11.183,
        "p50": 13.433,
        "p75": 14.967,
        "p95": 16.5,
        "max": 17.067
      },
      {
        "n": 147,
        "p5": 7.643,
        "p25": 11.617,
        "p50": 13.767,
        "p75": 15.367,
        "p95": 16.733,
        "max": 17.1
      },
      {
        "n": 93,
        "p5": 7.567,
        "p25": 11.483,
        "p50": 13.8,
        "p75": 15.367,
        "p95": 16.773,
        "max": 17.367
      },
      {
        "n": 137,
        "p5": 8.097,
        "p25": 11.65,
        "p50": 13.9,
        "p75": 15.467,
        "p95": 16.873,
        "max": 17.6
      },
      {
        "n": 115,
        "p5": 8.178,
        "p25": 11.725,
        "p50": 13.9,
        "p75": 15.433,
        "p95": 16.84,
        "max": 17.867
      },
      {
        "n": 190,
        "p5": 7.97,
        "p25": 11.858,
        "p50": 14.1,
        "p75": 15.6,
        "p95": 16.967,
        "max": 17.933
      },
      {
        "n": 392,
        "p5": 7.66,
        "p25": 11.725,
        "p50": 14.067,
        "p75": 15.567,
        "p95": 16.967,
        "max": 17.9
      },
      {
        "n": 239,
        "p5": 8.185,
        "p25": 12.017,
        "p50": 14.267,
        "p75": 15.733,
        "p95": 17.067,
        "max": 17.9
      },
      {
        "n": 133,
        "p5": 9.277,
        "p25": 12.583,
        "p50": 14.517,
        "p75": 15.9,
        "p95": 17.233,
        "max": 18
      },
      {
        "n": 174,
        "p5": 9.717,
        "p25": 13.033,
        "p50": 14.85,
        "p75": 16.167,
        "p95": 17.417,
        "max": 18.167
      },
      {
        "n": 171,
        "p5": 9.577,
        "p25": 13.067,
        "p50": 14.95,
        "p75": 16.233,
        "p95": 17.517,
        "max": 18.167
      },
      {
        "n": 95,
        "p5": 9.25,
        "p25": 13.067,
        "p50": 15.067,
        "p75": 16.35,
        "p95": 17.517,
        "max": 18.167
      },
      {
        "n": 195,
        "p5": 9.35,
        "p25": 12.867,
        "p50": 14.933,
        "p75": 16.317,
        "p95": 17.533,
        "max": 18.2
      },
      {
        "n": 415,
        "p5": 9.35,
        "p25": 12.683,
        "p50": 14.9,
        "p75": 16.35,
        "p95": 17.567,
        "max": 18.3
      },
      {
        "n": 212,
        "p5": 10.067,
        "p25": 13.175,
        "p50": 15.1,
        "p75": 16.5,
        "p95": 17.702,
        "max": 18.4
      },
      {
        "n": 200,
        "p5": 11.082,
        "p25": 13.717,
        "p50": 15.4,
        "p75": 16.7,
        "p95": 17.868,
        "max": 18.5
      },
      {
        "n": 210,
        "p5": 11.948,
        "p25": 14.183,
        "p50": 15.567,
        "p75": 16.817,
        "p95": 17.968,
        "max": 18.533
      },
      {
        "n": 163,
        "p5": 12.357,
        "p25": 14.292,
        "p50": 15.633,
        "p75": 16.917,
        "p95": 18.067,
        "max": 18.667
      },
      {
        "n": 226,
        "p5": 11.793,
        "p25": 14.25,
        "p50": 15.767,
        "p75": 17.008,
        "p95": 18.2,
        "max": 18.733
      },
      {
        "n": 158,
        "p5": 10.743,
        "p25": 13.95,
        "p50": 15.733,
        "p75": 16.992,
        "p95": 18.3,
        "max": 18.9
      },
      {
        "n": 391,
        "p5": 10.105,
        "p25": 13.675,
        "p50": 15.6,
        "p75": 16.992,
        "p95": 18.367,
        "max": 18.833
      },
      {
        "n": 172,
        "p5": 10.743,
        "p25": 13.942,
        "p50": 15.65,
        "p75": 17,
        "p95": 18.3,
        "max": 18.9
      },
      {
        "n": 168,
        "p5": 11.745,
        "p25": 14.325,
        "p50": 15.883,
        "p75": 17.175,
        "p95": 18.367,
        "max": 18.867
      },
      {
        "n": 212,
        "p5": 12.152,
        "p25": 14.567,
        "p50": 16.05,
        "p75": 17.275,
        "p95": 18.39,
        "max": 18.9
      },
      {
        "n": 167,
        "p5": 11.995,
        "p25": 14.633,
        "p50": 15.967,
        "p75": 17.233,
        "p95": 18.423,
        "max": 18.833
      },
      {
        "n": 166,
        "p5": 11.843,
        "p25": 14.8,
        "p50": 16.167,
        "p75": 17.425,
        "p95": 18.557,
        "max": 19
      },
      {
        "n": 221,
        "p5": 11.5,
        "p25": 14.733,
        "p50": 16.133,
        "p75": 17.325,
        "p95": 18.6,
        "max": 19.233
      },
      {
        "n": 479,
        "p5": 11.807,
        "p25": 14.8,
        "p50": 16.4,
        "p75": 17.567,
        "p95": 18.767,
        "max": 19.4
      },
      {
        "n": 229,
        "p5": 11.46,
        "p25": 14.533,
        "p50": 16.167,
        "p75": 17.333,
        "p95": 18.7,
        "max": 19.367
      },
      {
        "n": 353,
        "p5": 11.885,
        "p25": 14.725,
        "p50": 16.283,
        "p75": 17.442,
        "p95": 18.742,
        "max": 19.367
      },
      {
        "n": 256,
        "p5": 11.345,
        "p25": 14.592,
        "p50": 16.167,
        "p75": 17.35,
        "p95": 18.642,
        "max": 19.4
      },
      {
        "n": 288,
        "p5": 12.087,
        "p25": 14.867,
        "p50": 16.35,
        "p75": 17.55,
        "p95": 18.742,
        "max": 19.5
      },
      {
        "n": 318,
        "p5": 11.782,
        "p25": 14.775,
        "p50": 16.3,
        "p75": 17.575,
        "p95": 18.813,
        "max": 19.6
      },
      {
        "n": 373,
        "p5": 12.447,
        "p25": 15.108,
        "p50": 16.45,
        "p75": 17.733,
        "p95": 18.948,
        "max": 19.667
      },
      {
        "n": 300,
        "p5": 12.223,
        "p25": 15.125,
        "p50": 16.417,
        "p75": 17.742,
        "p95": 18.982,
        "max": 19.667
      },
      {
        "n": 304,
        "p5": 12.11,
        "p25": 15.058,
        "p50": 16.417,
        "p75": 17.742,
        "p95": 18.928,
        "max": 19.567
      },
      {
        "n": 145,
        "p5": 11.112,
        "p25": 14.658,
        "p50": 16.283,
        "p75": 17.675,
        "p95": 18.96,
        "max": 19.567
      },
      {
        "n": 281,
        "p5": 12.213,
        "p25": 15.3,
        "p50": 16.733,
        "p75": 17.967,
        "p95": 19.173,
        "max": 19.667
      },
      {
        "n": 37,
        "p5": 12.84,
        "p25": 15.633,
        "p50": 16.967,
        "p75": 18.2,
        "p95": 19.413,
        "max": 19.833
      },
      {
        "n": 351,
        "p5": 14.373,
        "p25": 16.3,
        "p50": 17.4,
        "p75": 18.5,
        "p95": 19.58,
        "max": 19.933
      },
      {
        "n": 281,
        "p5": 14.448,
        "p25": 16.333,
        "p50": 17.533,
        "p75": 18.6,
        "p95": 19.618,
        "max": 20
      },
      {
        "n": 230,
        "p5": 15.563,
        "p25": 16.933,
        "p50": 18,
        "p75": 18.867,
        "p95": 19.703,
        "max": 20
      }
    ],
    "B": [
      {
        "n": 212,
        "p5": 7.25,
        "p25": 10.667,
        "p50": 12.867,
        "p75": 14.367,
        "p95": 15.917,
        "max": 16.667
      },
      {
        "n": 69,
        "p5": 7.888,
        "p25": 11.008,
        "p50": 13.117,
        "p75": 14.667,
        "p95": 16.002,
        "max": 16.667
      },
      {
        "n": 98,
        "p5": 8.162,
        "p25": 11.358,
        "p50": 13.333,
        "p75": 14.867,
        "p95": 15.987,
        "max": 16.767
      },
      {
        "n": 76,
        "p5": 8.382,
        "p25": 11.425,
        "p50": 13.5,
        "p75": 14.867,
        "p95": 16.113,
        "max": 17.067
      },
      {
        "n": 93,
        "p5": 8.525,
        "p25": 11.758,
        "p50": 13.567,
        "p75": 14.833,
        "p95": 16.147,
        "max": 17.133
      },
      {
        "n": 256,
        "p5": 8.767,
        "p25": 11.825,
        "p50": 13.567,
        "p75": 14.8,
        "p95": 16.28,
        "max": 17.1
      },
      {
        "n": 316,
        "p5": 8.223,
        "p25": 11.758,
        "p50": 13.483,
        "p75": 14.867,
        "p95": 16.333,
        "max": 17.267
      },
      {
        "n": 188,
        "p5": 7.72,
        "p25": 11.5,
        "p50": 13.483,
        "p75": 14.967,
        "p95": 16.423,
        "max": 17.267
      },
      {
        "n": 147,
        "p5": 8.12,
        "p25": 11.867,
        "p50": 13.783,
        "p75": 15.167,
        "p95": 16.59,
        "max": 17.467
      },
      {
        "n": 101,
        "p5": 8.203,
        "p25": 12.067,
        "p50": 13.833,
        "p75": 15.133,
        "p95": 16.657,
        "max": 17.433
      },
      {
        "n": 137,
        "p5": 8.007,
        "p25": 12.25,
        "p50": 14.017,
        "p75": 15.208,
        "p95": 16.733,
        "max": 17.533
      },
      {
        "n": 116,
        "p5": 7.633,
        "p25": 12.192,
        "p50": 14.183,
        "p75": 15.475,
        "p95": 16.8,
        "max": 17.5
      },
      {
        "n": 190,
        "p5": 7.33,
        "p25": 11.917,
        "p50": 14.267,
        "p75": 15.608,
        "p95": 16.933,
        "max": 17.7
      },
      {
        "n": 392,
        "p5": 7.592,
        "p25": 11.867,
        "p50": 14.35,
        "p75": 15.633,
        "p95": 17.002,
        "max": 17.933
      },
      {
        "n": 240,
        "p5": 8.718,
        "p25": 12.392,
        "p50": 14.517,
        "p75": 15.667,
        "p95": 17.015,
        "max": 17.9
      },
      {
        "n": 133,
        "p5": 9.047,
        "p25": 12.942,
        "p50": 14.7,
        "p75": 15.867,
        "p95": 17.048,
        "max": 17.767
      },
      {
        "n": 174,
        "p5": 9.435,
        "p25": 13.458,
        "p50": 14.933,
        "p75": 16.1,
        "p95": 17.097,
        "max": 17.667
      },
      {
        "n": 171,
        "p5": 8.995,
        "p25": 13.558,
        "p50": 15,
        "p75": 16.233,
        "p95": 17.227,
        "max": 17.8
      },
      {
        "n": 95,
        "p5": 9.343,
        "p25": 13.633,
        "p50": 15.067,
        "p75": 16.333,
        "p95": 17.327,
        "max": 17.9
      },
      {
        "n": 195,
        "p5": 9.473,
        "p25": 13.35,
        "p50": 14.9,
        "p75": 16.233,
        "p95": 17.377,
        "max": 17.967
      },
      {
        "n": 415,
        "p5": 9.397,
        "p25": 12.942,
        "p50": 14.733,
        "p75": 16.1,
        "p95": 17.333,
        "max": 17.967
      },
      {
        "n": 212,
        "p5": 10.317,
        "p25": 13.225,
        "p50": 14.967,
        "p75": 16.267,
        "p95": 17.367,
        "max": 18.033
      },
      {
        "n": 201,
        "p5": 11.448,
        "p25": 13.892,
        "p50": 15.333,
        "p75": 16.6,
        "p95": 17.5,
        "max": 18.067
      },
      {
        "n": 210,
        "p5": 12.112,
        "p25": 14.5,
        "p50": 15.633,
        "p75": 16.833,
        "p95": 17.633,
        "max": 18.3
      },
      {
        "n": 163,
        "p5": 12.22,
        "p25": 14.608,
        "p50": 15.733,
        "p75": 16.9,
        "p95": 17.792,
        "max": 18.367
      },
      {
        "n": 226,
        "p5": 11.275,
        "p25": 14.508,
        "p50": 15.867,
        "p75": 16.933,
        "p95": 17.897,
        "max": 18.5
      },
      {
        "n": 158,
        "p5": 10.742,
        "p25": 14.108,
        "p50": 15.733,
        "p75": 16.9,
        "p95": 17.997,
        "max": 18.467
      },
      {
        "n": 392,
        "p5": 9.9,
        "p25": 13.592,
        "p50": 15.467,
        "p75": 16.8,
        "p95": 18.053,
        "max": 18.6
      },
      {
        "n": 172,
        "p5": 10.89,
        "p25": 13.725,
        "p50": 15.483,
        "p75": 16.867,
        "p95": 18.115,
        "max": 18.667
      },
      {
        "n": 168,
        "p5": 11.252,
        "p25": 14.125,
        "p50": 15.717,
        "p75": 17.142,
        "p95": 18.248,
        "max": 18.833
      },
      {
        "n": 212,
        "p5": 11.438,
        "p25": 14.533,
        "p50": 16.017,
        "p75": 17.325,
        "p95": 18.333,
        "max": 18.9
      },
      {
        "n": 167,
        "p5": 10.565,
        "p25": 14.542,
        "p50": 15.917,
        "p75": 17.283,
        "p95": 18.358,
        "max": 18.967
      },
      {
        "n": 166,
        "p5": 10.137,
        "p25": 14.642,
        "p50": 16.117,
        "p75": 17.408,
        "p95": 18.492,
        "max": 19.1
      },
      {
        "n": 221,
        "p5": 9.98,
        "p25": 14.575,
        "p50": 16.05,
        "p75": 17.325,
        "p95": 18.558,
        "max": 19.3
      },
      {
        "n": 479,
        "p5": 10.757,
        "p25": 14.667,
        "p50": 16.3,
        "p75": 17.533,
        "p95": 18.7,
        "max": 19.433
      },
      {
        "n": 229,
        "p5": 11.143,
        "p25": 14.5,
        "p50": 16.1,
        "p75": 17.267,
        "p95": 18.6,
        "max": 19.3
      },
      {
        "n": 353,
        "p5": 11.58,
        "p25": 14.633,
        "p50": 16.25,
        "p75": 17.433,
        "p95": 18.633,
        "max": 19.167
      },
      {
        "n": 256,
        "p5": 11.053,
        "p25": 14.567,
        "p50": 16.15,
        "p75": 17.3,
        "p95": 18.622,
        "max": 19.233
      },
      {
        "n": 288,
        "p5": 11.4,
        "p25": 14.733,
        "p50": 16.35,
        "p75": 17.525,
        "p95": 18.788,
        "max": 19.567
      },
      {
        "n": 318,
        "p5": 11.133,
        "p25": 14.7,
        "p50": 16.367,
        "p75": 17.525,
        "p95": 18.855,
        "max": 19.733
      },
      {
        "n": 373,
        "p5": 11.832,
        "p25": 15,
        "p50": 16.6,
        "p75": 17.725,
        "p95": 18.967,
        "max": 19.833
      },
      {
        "n": 300,
        "p5": 11.708,
        "p25": 14.967,
        "p50": 16.6,
        "p75": 17.733,
        "p95": 18.995,
        "max": 19.7
      },
      {
        "n": 304,
        "p5": 11.755,
        "p25": 15.067,
        "p50": 16.633,
        "p75": 17.733,
        "p95": 18.862,
        "max": 19.5
      },
      {
        "n": 145,
        "p5": 11.257,
        "p25": 14.633,
        "p50": 16.4,
        "p75": 17.633,
        "p95": 18.895,
        "max": 19.433
      },
      {
        "n": 281,
        "p5": 12.407,
        "p25": 15.333,
        "p50": 16.867,
        "p75": 17.967,
        "p95": 19.113,
        "max": 19.533
      },
      {
        "n": 37,
        "p5": 13.143,
        "p25": 15.5,
        "p50": 17.033,
        "p75": 18.2,
        "p95": 19.38,
        "max": 19.767
      },
      {
        "n": 351,
        "p5": 14.31,
        "p25": 16.267,
        "p50": 17.433,
        "p75": 18.567,
        "p95": 19.513,
        "max": 19.867
      },
      {
        "n": 281,
        "p5": 14.665,
        "p25": 16.367,
        "p50": 17.5,
        "p75": 18.667,
        "p95": 19.5,
        "max": 19.867
      },
      {
        "n": 230,
        "p5": 15.797,
        "p25": 17.033,
        "p50": 17.933,
        "p75": 18.967,
        "p95": 19.633,
        "max": 19.9
      }
    ],
    "MA": [
      {
        "n": 272,
        "p5": 7.512,
        "p25": 10.875,
        "p50": 13.133,
        "p75": 14.567,
        "p95": 15.855,
        "max": 16.7
      },
      {
        "n": 106,
        "p5": 8.063,
        "p25": 11.375,
        "p50": 13.483,
        "p75": 14.817,
        "p95": 15.973,
        "max": 16.9
      },
      {
        "n": 163,
        "p5": 8.112,
        "p25": 11.875,
        "p50": 13.867,
        "p75": 15.15,
        "p95": 16.138,
        "max": 16.9
      },
      {
        "n": 113,
        "p5": 8.403,
        "p25": 12.067,
        "p50": 13.833,
        "p75": 15.083,
        "p95": 16.155,
        "max": 16.967
      },
      {
        "n": 136,
        "p5": 8.537,
        "p25": 12.225,
        "p50": 13.833,
        "p75": 15.1,
        "p95": 16.322,
        "max": 17.133
      },
      {
        "n": 332,
        "p5": 8.803,
        "p25": 12.258,
        "p50": 13.733,
        "p75": 15.033,
        "p95": 16.442,
        "max": 17.3
      },
      {
        "n": 405,
        "p5": 8.355,
        "p25": 12.183,
        "p50": 13.733,
        "p75": 15.033,
        "p95": 16.433,
        "max": 17.367
      },
      {
        "n": 252,
        "p5": 7.767,
        "p25": 11.925,
        "p50": 13.7,
        "p75": 15.092,
        "p95": 16.467,
        "max": 17.167
      },
      {
        "n": 170,
        "p5": 8.57,
        "p25": 12.208,
        "p50": 13.933,
        "p75": 15.192,
        "p95": 16.533,
        "max": 17.167
      },
      {
        "n": 142,
        "p5": 8.575,
        "p25": 12.317,
        "p50": 13.933,
        "p75": 15.225,
        "p95": 16.51,
        "max": 17.333
      },
      {
        "n": 175,
        "p5": 8.957,
        "p25": 12.483,
        "p50": 14,
        "p75": 15.333,
        "p95": 16.543,
        "max": 17.5
      },
      {
        "n": 167,
        "p5": 8.32,
        "p25": 12.567,
        "p50": 14.067,
        "p75": 15.533,
        "p95": 16.657,
        "max": 17.733
      },
      {
        "n": 213,
        "p5": 8.23,
        "p25": 12.333,
        "p50": 14.2,
        "p75": 15.633,
        "p95": 16.813,
        "max": 17.8
      },
      {
        "n": 401,
        "p5": 8,
        "p25": 12.3,
        "p50": 14.3,
        "p75": 15.633,
        "p95": 16.9,
        "max": 17.9
      },
      {
        "n": 249,
        "p5": 8.893,
        "p25": 12.6,
        "p50": 14.467,
        "p75": 15.767,
        "p95": 16.967,
        "max": 17.8
      },
      {
        "n": 133,
        "p5": 9.515,
        "p25": 13.133,
        "p50": 14.767,
        "p75": 16.033,
        "p95": 17.112,
        "max": 17.767
      },
      {
        "n": 174,
        "p5": 10.032,
        "p25": 13.533,
        "p50": 15.067,
        "p75": 16.367,
        "p95": 17.258,
        "max": 17.8
      },
      {
        "n": 171,
        "p5": 9.795,
        "p25": 13.517,
        "p50": 15.133,
        "p75": 16.383,
        "p95": 17.288,
        "max": 18.133
      },
      {
        "n": 95,
        "p5": 9.558,
        "p25": 13.417,
        "p50": 15.067,
        "p75": 16.35,
        "p95": 17.225,
        "max": 18.2
      },
      {
        "n": 212,
        "p5": 9.505,
        "p25": 13.183,
        "p50": 14.967,
        "p75": 16.25,
        "p95": 17.292,
        "max": 18.333
      },
      {
        "n": 427,
        "p5": 9.307,
        "p25": 12.958,
        "p50": 14.917,
        "p75": 16.2,
        "p95": 17.348,
        "max": 18.267
      },
      {
        "n": 216,
        "p5": 10.388,
        "p25": 13.392,
        "p50": 15.117,
        "p75": 16.367,
        "p95": 17.567,
        "max": 18.367
      },
      {
        "n": 201,
        "p5": 11.355,
        "p25": 14.025,
        "p50": 15.35,
        "p75": 16.592,
        "p95": 17.667,
        "max": 18.333
      },
      {
        "n": 210,
        "p5": 12.203,
        "p25": 14.4,
        "p50": 15.567,
        "p75": 16.842,
        "p95": 17.833,
        "max": 18.333
      },
      {
        "n": 163,
        "p5": 12.378,
        "p25": 14.467,
        "p50": 15.767,
        "p75": 16.967,
        "p95": 17.933,
        "max": 18.4
      },
      {
        "n": 226,
        "p5": 11.877,
        "p25": 14.433,
        "p50": 15.933,
        "p75": 17.042,
        "p95": 18.067,
        "max": 18.533
      },
      {
        "n": 158,
        "p5": 11.037,
        "p25": 14.158,
        "p50": 15.817,
        "p75": 16.925,
        "p95": 18.082,
        "max": 18.767
      },
      {
        "n": 392,
        "p5": 10.028,
        "p25": 13.792,
        "p50": 15.583,
        "p75": 16.867,
        "p95": 18.115,
        "max": 18.867
      },
      {
        "n": 171,
        "p5": 10.812,
        "p25": 13.892,
        "p50": 15.65,
        "p75": 16.908,
        "p95": 18.137,
        "max": 19
      },
      {
        "n": 168,
        "p5": 11.667,
        "p25": 14.217,
        "p50": 15.867,
        "p75": 17.15,
        "p95": 18.288,
        "max": 18.967
      },
      {
        "n": 212,
        "p5": 12.187,
        "p25": 14.483,
        "p50": 16.033,
        "p75": 17.233,
        "p95": 18.355,
        "max": 18.9
      },
      {
        "n": 167,
        "p5": 11.983,
        "p25": 14.517,
        "p50": 15.9,
        "p75": 17.125,
        "p95": 18.325,
        "max": 18.833
      },
      {
        "n": 166,
        "p5": 11.495,
        "p25": 14.733,
        "p50": 16.2,
        "p75": 17.25,
        "p95": 18.425,
        "max": 18.933
      },
      {
        "n": 221,
        "p5": 11.075,
        "p25": 14.8,
        "p50": 16.2,
        "p75": 17.267,
        "p95": 18.428,
        "max": 19.133
      },
      {
        "n": 479,
        "p5": 11.067,
        "p25": 14.867,
        "p50": 16.433,
        "p75": 17.5,
        "p95": 18.637,
        "max": 19.3
      },
      {
        "n": 229,
        "p5": 11.087,
        "p25": 14.467,
        "p50": 16.033,
        "p75": 17.333,
        "p95": 18.583,
        "max": 19.3
      },
      {
        "n": 353,
        "p5": 11.453,
        "p25": 14.492,
        "p50": 16.2,
        "p75": 17.433,
        "p95": 18.68,
        "max": 19.3
      },
      {
        "n": 256,
        "p5": 11.032,
        "p25": 14.292,
        "p50": 16.067,
        "p75": 17.367,
        "p95": 18.647,
        "max": 19.333
      },
      {
        "n": 288,
        "p5": 11.412,
        "p25": 14.725,
        "p50": 16.4,
        "p75": 17.6,
        "p95": 18.8,
        "max": 19.533
      },
      {
        "n": 318,
        "p5": 11.305,
        "p25": 14.7,
        "p50": 16.333,
        "p75": 17.6,
        "p95": 18.9,
        "max": 19.733
      },
      {
        "n": 373,
        "p5": 11.925,
        "p25": 15.133,
        "p50": 16.6,
        "p75": 17.8,
        "p95": 19.035,
        "max": 19.867
      },
      {
        "n": 300,
        "p5": 11.958,
        "p25": 15.033,
        "p50": 16.6,
        "p75": 17.767,
        "p95": 19.068,
        "max": 19.767
      },
      {
        "n": 303,
        "p5": 11.832,
        "p25": 15.1,
        "p50": 16.633,
        "p75": 17.767,
        "p95": 19.028,
        "max": 19.7
      },
      {
        "n": 145,
        "p5": 11,
        "p25": 14.7,
        "p50": 16.467,
        "p75": 17.633,
        "p95": 18.927,
        "max": 19.7
      },
      {
        "n": 281,
        "p5": 12.28,
        "p25": 15.3,
        "p50": 16.833,
        "p75": 17.967,
        "p95": 19.073,
        "max": 19.8
      },
      {
        "n": 37,
        "p5": 13.08,
        "p25": 15.533,
        "p50": 17.067,
        "p75": 18.217,
        "p95": 19.247,
        "max": 19.867
      },
      {
        "n": 351,
        "p5": 14.547,
        "p25": 16.233,
        "p50": 17.433,
        "p75": 18.583,
        "p95": 19.513,
        "max": 19.867
      },
      {
        "n": 281,
        "p5": 14.697,
        "p25": 16.4,
        "p50": 17.567,
        "p75": 18.683,
        "p95": 19.567,
        "max": 19.933
      },
      {
        "n": 230,
        "p5": 15.893,
        "p25": 17.033,
        "p50": 17.967,
        "p75": 18.967,
        "p95": 19.667,
        "max": 19.967
      }
    ],
    "P": [
      {
        "n": 266,
        "p5": 7.4,
        "p25": 11.417,
        "p50": 13.1,
        "p75": 14.367,
        "p95": 15.883,
        "max": 16.867
      },
      {
        "n": 101,
        "p5": 7.797,
        "p25": 11.808,
        "p50": 13.367,
        "p75": 14.567,
        "p95": 15.992,
        "max": 16.7
      },
      {
        "n": 145,
        "p5": 8.003,
        "p25": 12.233,
        "p50": 13.733,
        "p75": 14.808,
        "p95": 16.122,
        "max": 16.667
      },
      {
        "n": 108,
        "p5": 7.37,
        "p25": 12.417,
        "p50": 13.8,
        "p75": 14.817,
        "p95": 16.11,
        "max": 16.667
      },
      {
        "n": 128,
        "p5": 7.823,
        "p25": 12.517,
        "p50": 13.867,
        "p75": 14.95,
        "p95": 16.243,
        "max": 16.933
      },
      {
        "n": 321,
        "p5": 8.133,
        "p25": 12.4,
        "p50": 13.8,
        "p75": 14.975,
        "p95": 16.355,
        "max": 17.167
      },
      {
        "n": 391,
        "p5": 8.433,
        "p25": 12.208,
        "p50": 13.733,
        "p75": 15.008,
        "p95": 16.433,
        "max": 17.367
      },
      {
        "n": 248,
        "p5": 7.867,
        "p25": 12.15,
        "p50": 13.8,
        "p75": 15.075,
        "p95": 16.467,
        "max": 17.433
      },
      {
        "n": 170,
        "p5": 8.933,
        "p25": 12.6,
        "p50": 14,
        "p75": 15.358,
        "p95": 16.567,
        "max": 17.367
      },
      {
        "n": 127,
        "p5": 8.657,
        "p25": 12.575,
        "p50": 14.133,
        "p75": 15.417,
        "p95": 16.567,
        "max": 17.367
      },
      {
        "n": 175,
        "p5": 8.798,
        "p25": 12.675,
        "p50": 14.2,
        "p75": 15.467,
        "p95": 16.667,
        "max": 17.433
      },
      {
        "n": 166,
        "p5": 8.518,
        "p25": 12.675,
        "p50": 14.267,
        "p75": 15.383,
        "p95": 16.78,
        "max": 17.533
      },
      {
        "n": 213,
        "p5": 8.362,
        "p25": 12.642,
        "p50": 14.333,
        "p75": 15.483,
        "p95": 16.93,
        "max": 17.683
      },
      {
        "n": 401,
        "p5": 8.52,
        "p25": 12.567,
        "p50": 14.367,
        "p75": 15.533,
        "p95": 16.99,
        "max": 17.783
      },
      {
        "n": 249,
        "p5": 8.987,
        "p25": 12.767,
        "p50": 14.533,
        "p75": 15.8,
        "p95": 17.123,
        "max": 18.25
      },
      {
        "n": 133,
        "p5": 9.862,
        "p25": 13.208,
        "p50": 14.833,
        "p75": 16.067,
        "p95": 17.24,
        "max": 18.633
      },
      {
        "n": 174,
        "p5": 10.495,
        "p25": 13.592,
        "p50": 15.1,
        "p75": 16.3,
        "p95": 17.397,
        "max": 18.667
      },
      {
        "n": 171,
        "p5": 10.078,
        "p25": 13.725,
        "p50": 15.233,
        "p75": 16.333,
        "p95": 17.35,
        "max": 18.433
      },
      {
        "n": 95,
        "p5": 9.637,
        "p25": 13.65,
        "p50": 15.217,
        "p75": 16.333,
        "p95": 17.432,
        "max": 18.233
      },
      {
        "n": 212,
        "p5": 9.325,
        "p25": 13.467,
        "p50": 15.083,
        "p75": 16.267,
        "p95": 17.393,
        "max": 18.267
      },
      {
        "n": 427,
        "p5": 9.272,
        "p25": 13.1,
        "p50": 14.983,
        "p75": 16.267,
        "p95": 17.468,
        "max": 18.3
      },
      {
        "n": 216,
        "p5": 10.405,
        "p25": 13.533,
        "p50": 15.167,
        "p75": 16.467,
        "p95": 17.553,
        "max": 18.267
      },
      {
        "n": 201,
        "p5": 11.48,
        "p25": 14.1,
        "p50": 15.517,
        "p75": 16.733,
        "p95": 17.675,
        "max": 18.4
      },
      {
        "n": 210,
        "p5": 12.363,
        "p25": 14.667,
        "p50": 15.783,
        "p75": 16.867,
        "p95": 17.83,
        "max": 18.5
      },
      {
        "n": 163,
        "p5": 12.372,
        "p25": 14.8,
        "p50": 15.883,
        "p75": 16.9,
        "p95": 17.897,
        "max": 18.467
      },
      {
        "n": 226,
        "p5": 11.742,
        "p25": 14.767,
        "p50": 16.017,
        "p75": 17.029,
        "p95": 18.063,
        "max": 18.633
      },
      {
        "n": 158,
        "p5": 10.958,
        "p25": 14.408,
        "p50": 15.917,
        "p75": 17.063,
        "p95": 18.167,
        "max": 18.767
      },
      {
        "n": 391,
        "p5": 10.102,
        "p25": 14,
        "p50": 15.75,
        "p75": 17.063,
        "p95": 18.267,
        "max": 18.9
      },
      {
        "n": 172,
        "p5": 10.913,
        "p25": 14.133,
        "p50": 15.8,
        "p75": 17.133,
        "p95": 18.333,
        "max": 18.9
      },
      {
        "n": 168,
        "p5": 11.333,
        "p25": 14.525,
        "p50": 16.033,
        "p75": 17.333,
        "p95": 18.4,
        "max": 18.833
      },
      {
        "n": 212,
        "p5": 11.422,
        "p25": 14.833,
        "p50": 16.233,
        "p75": 17.417,
        "p95": 18.467,
        "max": 18.933
      },
      {
        "n": 167,
        "p5": 10.76,
        "p25": 14.75,
        "p50": 16.067,
        "p75": 17.183,
        "p95": 18.433,
        "max": 18.933
      },
      {
        "n": 166,
        "p5": 10.723,
        "p25": 14.85,
        "p50": 16.233,
        "p75": 17.283,
        "p95": 18.533,
        "max": 19.067
      },
      {
        "n": 221,
        "p5": 10.815,
        "p25": 14.75,
        "p50": 16.2,
        "p75": 17.3,
        "p95": 18.568,
        "max": 19.167
      },
      {
        "n": 479,
        "p5": 11.045,
        "p25": 14.933,
        "p50": 16.4,
        "p75": 17.6,
        "p95": 18.702,
        "max": 19.367
      },
      {
        "n": 229,
        "p5": 10.612,
        "p25": 14.733,
        "p50": 16.233,
        "p75": 17.433,
        "p95": 18.635,
        "max": 19.4
      },
      {
        "n": 353,
        "p5": 10.872,
        "p25": 14.867,
        "p50": 16.333,
        "p75": 17.475,
        "p95": 18.633,
        "max": 19.367
      },
      {
        "n": 256,
        "p5": 10.827,
        "p25": 14.7,
        "p50": 16.35,
        "p75": 17.417,
        "p95": 18.633,
        "max": 19.367
      },
      {
        "n": 288,
        "p5": 11.355,
        "p25": 14.942,
        "p50": 16.483,
        "p75": 17.583,
        "p95": 18.733,
        "max": 19.433
      },
      {
        "n": 318,
        "p5": 11.317,
        "p25": 14.675,
        "p50": 16.483,
        "p75": 17.708,
        "p95": 18.847,
        "max": 19.55
      },
      {
        "n": 373,
        "p5": 11.681,
        "p25": 14.975,
        "p50": 16.625,
        "p75": 17.9,
        "p95": 19.013,
        "max": 19.633
      },
      {
        "n": 300,
        "p5": 11.519,
        "p25": 14.933,
        "p50": 16.6,
        "p75": 17.967,
        "p95": 19.08,
        "max": 19.667
      },
      {
        "n": 304,
        "p5": 11.046,
        "p25": 14.833,
        "p50": 16.533,
        "p75": 17.833,
        "p95": 19.067,
        "max": 19.683
      },
      {
        "n": 145,
        "p5": 10.647,
        "p25": 14.417,
        "p50": 16.375,
        "p75": 17.683,
        "p95": 18.967,
        "max": 19.6
      },
      {
        "n": 281,
        "p5": 12.313,
        "p25": 15.183,
        "p50": 16.967,
        "p75": 18.083,
        "p95": 19.173,
        "max": 19.7
      },
      {
        "n": 37,
        "p5": 13.35,
        "p25": 15.783,
        "p50": 17.25,
        "p75": 18.417,
        "p95": 19.34,
        "max": 19.733
      },
      {
        "n": 351,
        "p5": 14.65,
        "p25": 16.533,
        "p50": 17.65,
        "p75": 18.8,
        "p95": 19.573,
        "max": 19.867
      },
      {
        "n": 281,
        "p5": 14.674,
        "p25": 16.467,
        "p50": 17.617,
        "p75": 18.733,
        "p95": 19.533,
        "max": 19.85
      },
      {
        "n": 230,
        "p5": 15.915,
        "p25": 17.067,
        "p50": 18.067,
        "p75": 18.933,
        "p95": 19.6,
        "max": 19.867
      }
    ]
  },
  "deltas": {
    "GE1": {
      "early": {
        "n": 2337,
        "p5": -0.9,
        "p25": -0.1,
        "p50": 0.1,
        "p75": 0.4,
        "p95": 1.3
      },
      "mid": {
        "n": 4181,
        "p5": -0.7,
        "p25": -0.1,
        "p50": 0.1,
        "p75": 0.3,
        "p95": 0.9
      },
      "late": {
        "n": 3629,
        "p5": -0.9,
        "p25": -0.15,
        "p50": 0.075,
        "p75": 0.3,
        "p95": 1
      }
    },
    "GE2": {
      "early": {
        "n": 2336,
        "p5": -0.85,
        "p25": -0.1,
        "p50": 0.1,
        "p75": 0.4,
        "p95": 1.2
      },
      "mid": {
        "n": 4181,
        "p5": -0.7,
        "p25": -0.1,
        "p50": 0.1,
        "p75": 0.3,
        "p95": 1
      },
      "late": {
        "n": 3629,
        "p5": -0.9,
        "p25": -0.15,
        "p50": 0.1,
        "p75": 0.35,
        "p95": 1.0867
      }
    },
    "VP": {
      "early": {
        "n": 1740,
        "p5": -1,
        "p25": -0.2,
        "p50": 0.1,
        "p75": 0.42,
        "p95": 1.3
      },
      "mid": {
        "n": 4118,
        "p5": -0.8,
        "p25": -0.1,
        "p50": 0.1,
        "p75": 0.3333,
        "p95": 1
      },
      "late": {
        "n": 3630,
        "p5": -0.95,
        "p25": -0.2,
        "p50": 0.075,
        "p75": 0.3,
        "p95": 1.1
      }
    },
    "VA": {
      "early": {
        "n": 2338,
        "p5": -0.9,
        "p25": -0.1,
        "p50": 0.1,
        "p75": 0.4,
        "p95": 1.3
      },
      "mid": {
        "n": 4181,
        "p5": -0.75,
        "p25": -0.1,
        "p50": 0.1,
        "p75": 0.3,
        "p95": 1.1
      },
      "late": {
        "n": 3629,
        "p5": -0.9,
        "p25": -0.2,
        "p50": 0.0667,
        "p75": 0.3,
        "p95": 1
      }
    },
    "CG": {
      "early": {
        "n": 1730,
        "p5": -1,
        "p25": -0.2,
        "p50": 0.1,
        "p75": 0.4,
        "p95": 1.4
      },
      "mid": {
        "n": 4112,
        "p5": -0.7,
        "p25": -0.1,
        "p50": 0.1,
        "p75": 0.3,
        "p95": 1.1
      },
      "late": {
        "n": 3630,
        "p5": -0.9,
        "p25": -0.2,
        "p50": 0.08,
        "p75": 0.3,
        "p95": 1
      }
    },
    "B": {
      "early": {
        "n": 1736,
        "p5": -1.2,
        "p25": -0.2,
        "p50": 0.1,
        "p75": 0.4,
        "p95": 1.25
      },
      "mid": {
        "n": 4116,
        "p5": -0.7,
        "p25": -0.1,
        "p50": 0.1,
        "p75": 0.3,
        "p95": 1
      },
      "late": {
        "n": 3630,
        "p5": -0.9,
        "p25": -0.1333,
        "p50": 0.1,
        "p75": 0.3,
        "p95": 1.1
      }
    },
    "MA": {
      "early": {
        "n": 2337,
        "p5": -1,
        "p25": -0.15,
        "p50": 0.1,
        "p75": 0.4,
        "p95": 1.2
      },
      "mid": {
        "n": 4180,
        "p5": -0.7,
        "p25": -0.1,
        "p50": 0.1,
        "p75": 0.3167,
        "p95": 1.1
      },
      "late": {
        "n": 3629,
        "p5": -1.04,
        "p25": -0.15,
        "p50": 0.1,
        "p75": 0.325,
        "p95": 1.1
      }
    },
    "P": {
      "early": {
        "n": 2255,
        "p5": -0.986,
        "p25": -0.14,
        "p50": 0.1,
        "p75": 0.4,
        "p95": 1.3
      },
      "mid": {
        "n": 4178,
        "p5": -0.8,
        "p25": -0.12,
        "p50": 0.1,
        "p75": 0.35,
        "p95": 1
      },
      "late": {
        "n": 3630,
        "p5": -1,
        "p25": -0.15,
        "p50": 0.075,
        "p75": 0.3,
        "p95": 1.1
      }
    }
  },
  "archetypes": {
    "GE1": [
      {
        "L": 15.475,
        "k": 0.0709,
        "d0": 0.76,
        "share": 0.145,
        "n": 91
      },
      {
        "L": 16.173,
        "k": 0.0531,
        "d0": -19.06,
        "share": 0.24,
        "n": 150
      },
      {
        "L": 19.482,
        "k": 0.0407,
        "d0": -17.88,
        "share": 0.458,
        "n": 287
      },
      {
        "L": 19.487,
        "k": 0.0635,
        "d0": 13.64,
        "share": 0.157,
        "n": 98
      }
    ],
    "GE2": [
      {
        "L": 14.326,
        "k": 0.0703,
        "d0": -14.03,
        "share": 0.157,
        "n": 99
      },
      {
        "L": 18.4,
        "k": 0.0772,
        "d0": 17.98,
        "share": 0.136,
        "n": 86
      },
      {
        "L": 19.11,
        "k": 0.0403,
        "d0": -19.7,
        "share": 0.539,
        "n": 340
      },
      {
        "L": 19.144,
        "k": 0.0374,
        "d0": -0.08,
        "share": 0.168,
        "n": 106
      }
    ],
    "VP": [
      {
        "L": 14.557,
        "k": 0.0565,
        "d0": -15.07,
        "share": 0.195,
        "n": 120
      },
      {
        "L": 15.712,
        "k": 0.1348,
        "d0": 16.2,
        "share": 0.085,
        "n": 52
      },
      {
        "L": 19.09,
        "k": 0.0414,
        "d0": -19.11,
        "share": 0.507,
        "n": 311
      },
      {
        "L": 19.333,
        "k": 0.0423,
        "d0": 2.84,
        "share": 0.213,
        "n": 131
      }
    ],
    "VA": [
      {
        "L": 13.969,
        "k": 0.066,
        "d0": -7.08,
        "share": 0.146,
        "n": 91
      },
      {
        "L": 18.679,
        "k": 0.0442,
        "d0": -20.03,
        "share": 0.536,
        "n": 335
      },
      {
        "L": 18.876,
        "k": 0.0727,
        "d0": 16.58,
        "share": 0.117,
        "n": 73
      },
      {
        "L": 18.915,
        "k": 0.0438,
        "d0": -3.8,
        "share": 0.202,
        "n": 126
      }
    ],
    "CG": [
      {
        "L": 14.771,
        "k": 0.2381,
        "d0": 17.25,
        "share": 0.043,
        "n": 26
      },
      {
        "L": 15.067,
        "k": 0.0555,
        "d0": -17.2,
        "share": 0.207,
        "n": 125
      },
      {
        "L": 18.542,
        "k": 0.0523,
        "d0": 5.43,
        "share": 0.279,
        "n": 169
      },
      {
        "L": 19.187,
        "k": 0.0432,
        "d0": -18.12,
        "share": 0.471,
        "n": 285
      }
    ],
    "B": [
      {
        "L": 14.812,
        "k": 0.1256,
        "d0": 14.99,
        "share": 0.094,
        "n": 56
      },
      {
        "L": 15.603,
        "k": 0.0547,
        "d0": -16.84,
        "share": 0.244,
        "n": 146
      },
      {
        "L": 19.344,
        "k": 0.0397,
        "d0": -18.14,
        "share": 0.497,
        "n": 297
      },
      {
        "L": 19.515,
        "k": 0.0403,
        "d0": 5.46,
        "share": 0.166,
        "n": 99
      }
    ],
    "MA": [
      {
        "L": 15.123,
        "k": 0.0666,
        "d0": 3.12,
        "share": 0.119,
        "n": 74
      },
      {
        "L": 15.898,
        "k": 0.0534,
        "d0": -18.44,
        "share": 0.238,
        "n": 148
      },
      {
        "L": 19.331,
        "k": 0.0686,
        "d0": 14.37,
        "share": 0.138,
        "n": 86
      },
      {
        "L": 19.484,
        "k": 0.0386,
        "d0": -18.36,
        "share": 0.506,
        "n": 315
      }
    ],
    "P": [
      {
        "L": 13.448,
        "k": 0.1089,
        "d0": 8.93,
        "share": 0.069,
        "n": 42
      },
      {
        "L": 15.86,
        "k": 0.0561,
        "d0": -17.6,
        "share": 0.305,
        "n": 187
      },
      {
        "L": 18.837,
        "k": 0.057,
        "d0": 6.69,
        "share": 0.15,
        "n": 92
      },
      {
        "L": 19.353,
        "k": 0.0407,
        "d0": -19.17,
        "share": 0.476,
        "n": 292
      }
    ]
  },
  "totalBands": [
    {
      "n": 272,
      "p5": 36.956,
      "p25": 54.288,
      "p50": 64.845,
      "p75": 71.229,
      "p95": 78.525,
      "max": 81.367
    },
    {
      "n": 106,
      "p5": 40.77,
      "p25": 56.879,
      "p50": 66.31,
      "p75": 72.771,
      "p95": 79.034,
      "max": 82.133
    },
    {
      "n": 163,
      "p5": 43.253,
      "p25": 58.963,
      "p50": 68.042,
      "p75": 74.237,
      "p95": 79.57,
      "max": 82.75
    },
    {
      "n": 113,
      "p5": 43.044,
      "p25": 59.942,
      "p50": 68.35,
      "p75": 74.479,
      "p95": 80.095,
      "max": 83.967
    },
    {
      "n": 136,
      "p5": 43.806,
      "p25": 60.5,
      "p50": 68.533,
      "p75": 74.638,
      "p95": 80.472,
      "max": 84.367
    },
    {
      "n": 333,
      "p5": 44.306,
      "p25": 60.683,
      "p50": 68.333,
      "p75": 74.488,
      "p95": 80.982,
      "max": 84.95
    },
    {
      "n": 406,
      "p5": 43.087,
      "p25": 60.054,
      "p50": 68.217,
      "p75": 74.088,
      "p95": 81.229,
      "max": 84.917
    },
    {
      "n": 252,
      "p5": 40.808,
      "p25": 59.079,
      "p50": 68.517,
      "p75": 73.954,
      "p95": 81.677,
      "max": 84.817
    },
    {
      "n": 170,
      "p5": 43.046,
      "p25": 61.104,
      "p50": 69.417,
      "p75": 74.904,
      "p95": 82.41,
      "max": 85.017
    },
    {
      "n": 142,
      "p5": 42.859,
      "p25": 61.1,
      "p50": 69.583,
      "p75": 75.233,
      "p95": 82.586,
      "max": 85.317
    },
    {
      "n": 175,
      "p5": 44.028,
      "p25": 62.275,
      "p50": 69.9,
      "p75": 75.875,
      "p95": 82.993,
      "max": 85.95
    },
    {
      "n": 167,
      "p5": 43.075,
      "p25": 62.375,
      "p50": 70.383,
      "p75": 76.5,
      "p95": 83.447,
      "max": 86.533
    },
    {
      "n": 215,
      "p5": 42.62,
      "p25": 61.567,
      "p50": 70.875,
      "p75": 77.267,
      "p95": 84.065,
      "max": 87.3
    },
    {
      "n": 403,
      "p5": 42.01,
      "p25": 60.4,
      "p50": 71.325,
      "p75": 77.508,
      "p95": 84.447,
      "max": 87.867
    },
    {
      "n": 249,
      "p5": 46.248,
      "p25": 61.558,
      "p50": 72.175,
      "p75": 78.35,
      "p95": 84.7,
      "max": 88.217
    },
    {
      "n": 133,
      "p5": 49.891,
      "p25": 63.967,
      "p50": 73.583,
      "p75": 79.329,
      "p95": 85.524,
      "max": 88.367
    },
    {
      "n": 174,
      "p5": 51.726,
      "p25": 66.367,
      "p50": 74.683,
      "p75": 80.837,
      "p95": 86.073,
      "max": 88.633
    },
    {
      "n": 171,
      "p5": 49.343,
      "p25": 66.433,
      "p50": 75.1,
      "p75": 81.371,
      "p95": 86.381,
      "max": 89.05
    },
    {
      "n": 95,
      "p5": 48.924,
      "p25": 66.417,
      "p50": 75.208,
      "p75": 81.571,
      "p95": 86.308,
      "max": 89.45
    },
    {
      "n": 212,
      "p5": 48.952,
      "p25": 65.458,
      "p50": 74.792,
      "p75": 81.121,
      "p95": 86.473,
      "max": 89.892
    },
    {
      "n": 427,
      "p5": 48.911,
      "p25": 64.142,
      "p50": 74.283,
      "p75": 80.617,
      "p95": 86.69,
      "max": 89.942
    },
    {
      "n": 218,
      "p5": 52.869,
      "p25": 66.025,
      "p50": 75.042,
      "p75": 81.638,
      "p95": 87.355,
      "max": 90.258
    },
    {
      "n": 201,
      "p5": 57.203,
      "p25": 69.046,
      "p50": 76.317,
      "p75": 82.817,
      "p95": 88.083,
      "max": 90.65
    },
    {
      "n": 210,
      "p5": 60.947,
      "p25": 71.846,
      "p50": 77.742,
      "p75": 83.679,
      "p95": 88.642,
      "max": 91.217
    },
    {
      "n": 163,
      "p5": 61.447,
      "p25": 72.45,
      "p50": 78.558,
      "p75": 84.016,
      "p95": 89.071,
      "max": 91.85
    },
    {
      "n": 226,
      "p5": 58.445,
      "p25": 72.062,
      "p50": 79.3,
      "p75": 84.471,
      "p95": 89.515,
      "max": 92.2
    },
    {
      "n": 158,
      "p5": 55.094,
      "p25": 70.212,
      "p50": 78.792,
      "p75": 84.579,
      "p95": 90.042,
      "max": 92.6
    },
    {
      "n": 392,
      "p5": 52.209,
      "p25": 68.746,
      "p50": 77.867,
      "p75": 84.408,
      "p95": 90.356,
      "max": 92.767
    },
    {
      "n": 172,
      "p5": 56.674,
      "p25": 69.579,
      "p50": 78.183,
      "p75": 84.675,
      "p95": 90.776,
      "max": 92.867
    },
    {
      "n": 168,
      "p5": 60.541,
      "p25": 71.246,
      "p50": 79.217,
      "p75": 85.592,
      "p95": 91.241,
      "max": 93.333
    },
    {
      "n": 212,
      "p5": 62.991,
      "p25": 72.467,
      "p50": 80.125,
      "p75": 85.95,
      "p95": 91.611,
      "max": 93.617
    },
    {
      "n": 167,
      "p5": 61.141,
      "p25": 72.571,
      "p50": 79.675,
      "p75": 85.413,
      "p95": 91.378,
      "max": 94.433
    },
    {
      "n": 166,
      "p5": 59.632,
      "p25": 73.354,
      "p50": 80.767,
      "p75": 86.171,
      "p95": 91.913,
      "max": 94.983
    },
    {
      "n": 221,
      "p5": 57.425,
      "p25": 73.217,
      "p50": 80.583,
      "p75": 86.038,
      "p95": 92.2,
      "max": 95.633
    },
    {
      "n": 479,
      "p5": 58.118,
      "p25": 73.971,
      "p50": 81.7,
      "p75": 87.083,
      "p95": 93.093,
      "max": 95.933
    },
    {
      "n": 229,
      "p5": 56.885,
      "p25": 72.704,
      "p50": 80.483,
      "p75": 85.975,
      "p95": 92.873,
      "max": 95.783
    },
    {
      "n": 353,
      "p5": 58.348,
      "p25": 73.333,
      "p50": 80.942,
      "p75": 86.575,
      "p95": 93.219,
      "max": 95.783
    },
    {
      "n": 256,
      "p5": 57.399,
      "p25": 72.421,
      "p50": 80.492,
      "p75": 86.358,
      "p95": 93.237,
      "max": 95.867
    },
    {
      "n": 288,
      "p5": 60.378,
      "p25": 74.117,
      "p50": 81.667,
      "p75": 87.383,
      "p95": 93.812,
      "max": 96.717
    },
    {
      "n": 318,
      "p5": 58.937,
      "p25": 73.85,
      "p50": 81.808,
      "p75": 87.492,
      "p95": 94.069,
      "max": 97.542
    },
    {
      "n": 373,
      "p5": 61.13,
      "p25": 75.85,
      "p50": 82.992,
      "p75": 88.513,
      "p95": 94.743,
      "max": 98.325
    },
    {
      "n": 300,
      "p5": 60.187,
      "p25": 75.754,
      "p50": 83.017,
      "p75": 88.556,
      "p95": 94.938,
      "max": 98.092
    },
    {
      "n": 304,
      "p5": 60.723,
      "p25": 75.804,
      "p50": 83.133,
      "p75": 88.673,
      "p95": 94.731,
      "max": 97.7
    },
    {
      "n": 145,
      "p5": 58.103,
      "p25": 73.633,
      "p50": 82.133,
      "p75": 88.044,
      "p95": 94.33,
      "max": 97.467
    },
    {
      "n": 281,
      "p5": 64.293,
      "p25": 76.917,
      "p50": 84.083,
      "p75": 89.775,
      "p95": 94.97,
      "max": 98.133
    },
    {
      "n": 37,
      "p5": 66.977,
      "p25": 78.417,
      "p50": 85.233,
      "p75": 90.767,
      "p95": 95.94,
      "max": 98.583
    },
    {
      "n": 351,
      "p5": 73.043,
      "p25": 81.767,
      "p50": 87.258,
      "p75": 92.583,
      "p95": 97.04,
      "max": 98.933
    },
    {
      "n": 281,
      "p5": 74.25,
      "p25": 82.167,
      "p50": 87.754,
      "p75": 92.973,
      "p95": 97.326,
      "max": 98.967
    },
    {
      "n": 230,
      "p5": 80.667,
      "p25": 85.25,
      "p50": 89.75,
      "p75": 94.488,
      "p95": 97.685,
      "max": 99.117
    }
  ],
  "totalDeltas": {
    "early": {
      "n": 2341,
      "p5": -1.6,
      "p25": 0,
      "p50": 0.55,
      "p75": 1.3,
      "p95": 3.05
    },
    "mid": {
      "n": 4183,
      "p5": -1.15,
      "p25": 0,
      "p50": 0.475,
      "p75": 1.0854,
      "p95": 2.84
    },
    "late": {
      "n": 3630,
      "p5": -2.15,
      "p25": -0.1667,
      "p50": 0.375,
      "p75": 1.025,
      "p95": 2.8296
    }
  }
}
